pathlibs3/__init__.py
pathlibs3/pathlibs3.py
pathlibs3-1.1.8.dist-info/METADATA
pathlibs3-1.1.8.dist-info/WHEEL
pathlibs3-1.1.8.dist-info/RECORD
