Metadata-Version: 2.1
Name: pathlibs3
Version: 1.1.8
Summary: S3 navigation using object, inspired by pathlib.Path
Home-page: https://github.com/thibaultbl/s3_navigator
License: Apache-2.0
Author: thibault.blanc
Requires-Python: >=3.10
Classifier: License :: OSI Approved :: Apache Software License
Classifier: Programming Language :: Python :: 3
Classifier: Programming Language :: Python :: 3.10
Classifier: Programming Language :: Python :: 3.11
Provides-Extra: docs
Requires-Dist: Sphinx ; extra == "docs"
Requires-Dist: boto3
Requires-Dist: sphinx-rtd-theme ; extra == "docs"
Requires-Dist: sphinxcontrib-napoleon ; extra == "docs"
Requires-Dist: urllib3
